tox_ltt/__init__.py
tox_ltt/_version.py
tox_ltt/plugin.py
tox_ltt/py.typed
tox_ltt-0.4.2.dist-info/LICENSE
tox_ltt-0.4.2.dist-info/METADATA
tox_ltt-0.4.2.dist-info/WHEEL
tox_ltt-0.4.2.dist-info/entry_points.txt
tox_ltt-0.4.2.dist-info/top_level.txt
tox_ltt-0.4.2.dist-info/RECORD
