Metadata-Version: 2.1
Name: tox-ltt
Version: 0.4.2
Summary: Install PyTorch distributions with light-the-torch
Home-page: https://github.com/pmeier/tox-ltt
Author: Philip Meier
Author-email: github.pmeier@posteo.de
License: BSD-3-Clause
Project-URL: Source, https://github.com/pmeier/tox-ltt
Project-URL: Tracker, https://github.com/pmeier/tox-ltt/issues
Keywords: light-the-torch,pytorch,cuda,pip,install,tox,plugin
Platform: any
Classifier: Development Status :: 3 - Alpha
Classifier: License :: OSI Approved :: BSD License
Classifier: Programming Language :: Python :: 3.6
Classifier: Programming Language :: Python :: 3.7
Classifier: Programming Language :: Python :: 3.8
Classifier: Typing :: Typed
Requires-Python: >=3.6
License-File: LICENSE
Requires-Dist: light-the-torch (>=0.3.3)
Requires-Dist: tox
